rypython/__init__.py
rypython/randas/__init__.py
rypython/rex/__init__.py
rypython/rexcel/__init__.py
rypython/rexcel/formats.py
rypython/ry365/__init__.py
rypython/ry365/account.py
rypython/ry365/drive.py
rypython/ry365/excel.py
rypython/ry365/logger.py
rypython/ry365/sharepoint.py
rypython/rysg/__init__.py
rypython/rysg/windows.py
rypython/ryteams/__init__.py
rypython/rytime/__init__.py
rypython-1.7.11.dist-info/WHEEL
rypython-1.7.11.dist-info/METADATA
rypython-1.7.11.dist-info/RECORD
